{
  "sections": {
    "image_banner": {
      "type": "image-banner",
      "disabled": true,
      "blocks": {
        "heading": {
          "type": "heading",
          "settings": {
            "heading": "Browse our latest products",
            "heading_size": "h0"
          }
        },
        "button": {
          "type": "buttons",
          "settings": {
            "button_label_1": "Shop all",
            "button_link_1": "shopify:\/\/collections\/all",
            "button_style_secondary_1": true,
            "button_label_2": "",
            "button_link_2": "",
            "button_style_secondary_2": false
          }
        }
      },
      "block_order": [
        "heading",
        "button"
      ],
      "settings": {
        "image_overlay_opacity": 40,
        "image_height": "large",
        "desktop_content_position": "bottom-center",
        "show_text_box": false,
        "desktop_content_alignment": "center",
        "color_scheme": "background-1",
        "image_behavior": "none",
        "mobile_content_alignment": "center",
        "stack_images_on_mobile": false,
        "show_text_below": false
      }
    },
    "featured_collection": {
      "type": "featured-collection",
      "disabled": true,
      "settings": {
        "title": "Featured products",
        "heading_size": "h2",
        "description": "",
        "show_description": false,
        "description_style": "body",
        "collection": "all",
        "products_to_show": 8,
        "columns_desktop": 4,
        "full_width": false,
        "show_view_all": true,
        "view_all_style": "solid",
        "enable_desktop_slider": false,
        "color_scheme": "background-1",
        "image_ratio": "adapt",
        "show_secondary_image": true,
        "show_vendor": false,
        "show_rating": false,
        "enable_quick_add": false,
        "columns_mobile": "2",
        "swipe_on_mobile": false,
        "padding_top": 44,
        "padding_bottom": 36
      }
    },
    "8940e5a0-75f4-4d40-b6b2-021fe311c881": {
      "type": "hero-banner",
      "blocks": {
        "e7da1bed-06b1-4b2c-acea-f85acb4c3132": {
          "type": "text",
          "settings": {
            "title": "",
            "subtitile": ""
          }
        }
      },
      "block_order": [
        "e7da1bed-06b1-4b2c-acea-f85acb4c3132"
      ],
      "settings": {
      }
    },
    "2c03278a-678e-4221-9c2b-0ed4f6756b31": {
      "type": "rich-text",
      "blocks": {
        "template--18613229912345__2c03278a-678e-4221-9c2b-0ed4f6756b31-16813659714e331a0d-0": {
          "type": "heading",
          "settings": {
            "heading": "Talk about your brand",
            "heading_size": "h1"
          }
        },
        "template--18613229912345__2c03278a-678e-4221-9c2b-0ed4f6756b31-16813659714e331a0d-1": {
          "type": "text",
          "settings": {
            "text": "<p>Share information about your brand with your customers. Describe a product, make announcements, or welcome customers to your store.<\/p>"
          }
        },
        "template--18613229912345__2c03278a-678e-4221-9c2b-0ed4f6756b31-16813659714e331a0d-2": {
          "type": "button",
          "settings": {
            "button_label": "Button label",
            "button_link": "",
            "button_style_secondary": false,
            "button_label_2": "",
            "button_link_2": "",
            "button_style_secondary_2": false
          }
        }
      },
      "block_order": [
        "template--18613229912345__2c03278a-678e-4221-9c2b-0ed4f6756b31-16813659714e331a0d-0",
        "template--18613229912345__2c03278a-678e-4221-9c2b-0ed4f6756b31-16813659714e331a0d-1",
        "template--18613229912345__2c03278a-678e-4221-9c2b-0ed4f6756b31-16813659714e331a0d-2"
      ],
      "settings": {
        "desktop_content_position": "center",
        "content_alignment": "center",
        "color_scheme": "background-1",
        "full_width": true,
        "padding_top": 40,
        "padding_bottom": 52
      }
    },
    "37a5b451-1942-4acd-b67d-76f9b364d57c": {
      "type": "image-banner",
      "blocks": {
        "template--18613229912345__37a5b451-1942-4acd-b67d-76f9b364d57c-16814537711122aa7e-0": {
          "type": "heading",
          "settings": {
            "heading": "Image banner",
            "heading_size": "h1"
          }
        },
        "template--18613229912345__37a5b451-1942-4acd-b67d-76f9b364d57c-16814537711122aa7e-1": {
          "type": "text",
          "settings": {
            "text": "Give customers details about the banner image(s) or content on the template.",
            "text_style": "body"
          }
        }
      },
      "block_order": [
        "template--18613229912345__37a5b451-1942-4acd-b67d-76f9b364d57c-16814537711122aa7e-0",
        "template--18613229912345__37a5b451-1942-4acd-b67d-76f9b364d57c-16814537711122aa7e-1"
      ],
      "settings": {
        "image": "shopify:\/\/shop_images\/Screenshot_from_2023-03-02_10-52-01.png",
        "image_overlay_opacity": 0,
        "image_height": "medium",
        "desktop_content_position": "middle-center",
        "show_text_box": true,
        "desktop_content_alignment": "center",
        "color_scheme": "background-1",
        "image_behavior": "none",
        "mobile_content_alignment": "center",
        "stack_images_on_mobile": true,
        "show_text_below": true
      }
    },
    "7fb26128-c803-4d48-b431-d909de0248da": {
      "type": "excersize-liquid",
      "blocks": {
        "template--18613229912345__7fb26128-c803-4d48-b431-d909de0248da-1681722046f32a4768-0": {
          "type": "text",
          "settings": {
            "exercise": ""
          }
        }
      },
      "block_order": [
        "template--18613229912345__7fb26128-c803-4d48-b431-d909de0248da-1681722046f32a4768-0"
      ],
      "settings": {
      }
    },
    "54052548-6bd9-4bd6-b1c0-abcec85d5938": {
      "type": "slideshow",
      "blocks": {
        "template--18613229912345__54052548-6bd9-4bd6-b1c0-abcec85d5938-168172218442425c35-0": {
          "type": "slide",
          "settings": {
            "image": "shopify:\/\/shop_images\/person-fishing-on-the-beach-is-silhouetted-at-sunset.jpg",
            "heading": "Image slide",
            "heading_size": "h1",
            "subheading": "Tell your brand's story through images",
            "button_label": "Button label",
            "link": "",
            "button_style_secondary": false,
            "box_align": "middle-center",
            "show_text_box": true,
            "text_alignment": "center",
            "image_overlay_opacity": 0,
            "color_scheme": "background-1",
            "text_alignment_mobile": "center"
          }
        },
        "template--18613229912345__54052548-6bd9-4bd6-b1c0-abcec85d5938-168172218442425c35-1": {
          "type": "slide",
          "settings": {
            "image": "shopify:\/\/shop_images\/golden-autumn-leaves.jpg",
            "heading": "Image slide",
            "heading_size": "h1",
            "subheading": "Tell your brand's story through images",
            "button_label": "Button label",
            "link": "",
            "button_style_secondary": false,
            "box_align": "middle-center",
            "show_text_box": true,
            "text_alignment": "center",
            "image_overlay_opacity": 0,
            "color_scheme": "background-1",
            "text_alignment_mobile": "center"
          }
        }
      },
      "block_order": [
        "template--18613229912345__54052548-6bd9-4bd6-b1c0-abcec85d5938-168172218442425c35-0",
        "template--18613229912345__54052548-6bd9-4bd6-b1c0-abcec85d5938-168172218442425c35-1"
      ],
      "settings": {
        "layout": "full_bleed",
        "slide_height": "medium",
        "slider_visual": "counter",
        "auto_rotate": false,
        "change_slides_speed": 5,
        "image_behavior": "none",
        "show_text_below": true,
        "accessibility_info": "Slideshow about our brand"
      }
    }
  },
  "order": [
    "image_banner",
    "featured_collection",
    "8940e5a0-75f4-4d40-b6b2-021fe311c881",
    "2c03278a-678e-4221-9c2b-0ed4f6756b31",
    "37a5b451-1942-4acd-b67d-76f9b364d57c",
    "7fb26128-c803-4d48-b431-d909de0248da",
    "54052548-6bd9-4bd6-b1c0-abcec85d5938"
  ]
}